A2G/SeqIO.py
A2G/__init__.py
A2G/__version__.py
A2G/align2consensus.py
A2G-2020.0.1.data/scripts/A2G
A2G-2020.0.1.data/scripts/A2G_mpi
A2G-2020.0.1.dist-info/METADATA
A2G-2020.0.1.dist-info/WHEEL
A2G-2020.0.1.dist-info/top_level.txt
A2G-2020.0.1.dist-info/RECORD
