Metadata-Version: 2.1
Name: A2G
Version: 2020.0.1
Summary: Accurarate amplicon alignment to gene consensus
Home-page: https://github.com/jshleap/A2G
Author: jshleap
Author-email: jshleap@gmail.com
License: GNU v3
Platform: UNKNOWN
Requires-Python: >=3.6
Requires-Dist: scipy (>=1.3.3)
Requires-Dist: numpy (>=1.16.3)
Requires-Dist: scikit-learn (>=0.22.0)
Requires-Dist: tqdm (>=4.38.0)
Requires-Dist: biopython (>=1.75)
Requires-Dist: pandas (>=0.25.3)
Requires-Dist: joblib (>=0.14.0)
Requires-Dist: justblast (>=2020.0.1)
Requires-Dist: matplotlib (>=3.1.1)
Requires-Dist: plyvel (>=1.1.0)
Requires-Dist: pyfaidx (>=0.5.8)
Requires-Dist: termcolor (>=1.1.0)
